<?xml version="1.0" encoding="UTF-8" standalone="yes"?>
<template encoding-version="1.3">
    <description></description>
    <groupId>31a68bd1-0189-1000-3650-0f186f8f2452</groupId>
    <name>pseudo_facebook_template</name>
    <snippet>
        <processGroups>
            <id>3937ac05-5578-3ca8-0000-000000000000</id>
            <parentGroupId>5a0fed5a-2898-3c7c-0000-000000000000</parentGroupId>
            <position>
                <x>0.0</x>
                <y>0.0</y>
            </position>
            <versionedComponentId>3937ac05-5578-3ca8-a618-f225242e76ce</versionedComponentId>
            <comments></comments>
            <contents>
                <connections>
                    <id>17b5f6e8-93c3-3fd1-0000-000000000000</id>
                    <parentGroupId>3937ac05-5578-3ca8-0000-000000000000</parentGroupId>
                    <versionedComponentId>17b5f6e8-93c3-3fd1-9a46-3dbd00071724</versionedComponentId>
                    <backPressureDataSizeThreshold>1 GB</backPressureDataSizeThreshold>
                    <backPressureObjectThreshold>10000</backPressureObjectThreshold>
                    <destination>
                        <groupId>3937ac05-5578-3ca8-0000-000000000000</groupId>
                        <id>977518bf-ca05-320d-0000-000000000000</id>
                        <type>PROCESSOR</type>
                        <versionedComponentId>977518bf-ca05-320d-aebf-e1dab3178566</versionedComponentId>
                    </destination>
                    <flowFileExpiration>0 sec</flowFileExpiration>
                    <labelIndex>1</labelIndex>
                    <loadBalanceCompression>DO_NOT_COMPRESS</loadBalanceCompression>
                    <loadBalancePartitionAttribute></loadBalancePartitionAttribute>
                    <loadBalanceStatus>LOAD_BALANCE_NOT_CONFIGURED</loadBalanceStatus>
                    <loadBalanceStrategy>DO_NOT_LOAD_BALANCE</loadBalanceStrategy>
                    <name></name>
                    <selectedRelationships>Response</selectedRelationships>
                    <source>
                        <groupId>3937ac05-5578-3ca8-0000-000000000000</groupId>
                        <id>11d2269b-4363-39af-0000-000000000000</id>
                        <type>PROCESSOR</type>
                        <versionedComponentId>11d2269b-4363-39af-9cd2-a6be9124ba1e</versionedComponentId>
                    </source>
                    <zIndex>0</zIndex>
                </connections>
                <connections>
                    <id>55ac325d-c7fa-3e83-0000-000000000000</id>
                    <parentGroupId>3937ac05-5578-3ca8-0000-000000000000</parentGroupId>
                    <versionedComponentId>55ac325d-c7fa-3e83-b921-78f9cfd21f1b</versionedComponentId>
                    <backPressureDataSizeThreshold>1 GB</backPressureDataSizeThreshold>
                    <backPressureObjectThreshold>10000</backPressureObjectThreshold>
                    <destination>
                        <groupId>3937ac05-5578-3ca8-0000-000000000000</groupId>
                        <id>f305bd82-323d-3bcb-0000-000000000000</id>
                        <type>PROCESSOR</type>
                        <versionedComponentId>f305bd82-323d-3bcb-850e-0cc26b69df3d</versionedComponentId>
                    </destination>
                    <flowFileExpiration>0 sec</flowFileExpiration>
                    <labelIndex>1</labelIndex>
                    <loadBalanceCompression>DO_NOT_COMPRESS</loadBalanceCompression>
                    <loadBalancePartitionAttribute></loadBalancePartitionAttribute>
                    <loadBalanceStatus>LOAD_BALANCE_NOT_CONFIGURED</loadBalanceStatus>
                    <loadBalanceStrategy>DO_NOT_LOAD_BALANCE</loadBalanceStrategy>
                    <name></name>
                    <selectedRelationships>success</selectedRelationships>
                    <source>
                        <groupId>3937ac05-5578-3ca8-0000-000000000000</groupId>
                        <id>79315e66-d893-3ed7-0000-000000000000</id>
                        <type>PROCESSOR</type>
                        <versionedComponentId>79315e66-d893-3ed7-9816-149dd96bc8d5</versionedComponentId>
                    </source>
                    <zIndex>0</zIndex>
                </connections>
                <connections>
                    <id>97aed4a7-5ac0-3436-0000-000000000000</id>
                    <parentGroupId>3937ac05-5578-3ca8-0000-000000000000</parentGroupId>
                    <versionedComponentId>97aed4a7-5ac0-3436-a73d-c4035ba133ff</versionedComponentId>
                    <backPressureDataSizeThreshold>1 GB</backPressureDataSizeThreshold>
                    <backPressureObjectThreshold>10000</backPressureObjectThreshold>
                    <destination>
                        <groupId>3937ac05-5578-3ca8-0000-000000000000</groupId>
                        <id>977518bf-ca05-320d-0000-000000000000</id>
                        <type>PROCESSOR</type>
                        <versionedComponentId>977518bf-ca05-320d-aebf-e1dab3178566</versionedComponentId>
                    </destination>
                    <flowFileExpiration>0 sec</flowFileExpiration>
                    <labelIndex>1</labelIndex>
                    <loadBalanceCompression>DO_NOT_COMPRESS</loadBalanceCompression>
                    <loadBalancePartitionAttribute></loadBalancePartitionAttribute>
                    <loadBalanceStatus>LOAD_BALANCE_NOT_CONFIGURED</loadBalanceStatus>
                    <loadBalanceStrategy>DO_NOT_LOAD_BALANCE</loadBalanceStrategy>
                    <name></name>
                    <selectedRelationships>success</selectedRelationships>
                    <source>
                        <groupId>3937ac05-5578-3ca8-0000-000000000000</groupId>
                        <id>79315e66-d893-3ed7-0000-000000000000</id>
                        <type>PROCESSOR</type>
                        <versionedComponentId>79315e66-d893-3ed7-9816-149dd96bc8d5</versionedComponentId>
                    </source>
                    <zIndex>0</zIndex>
                </connections>
                <controllerServices>
                    <id>faab8056-66ab-3d18-0000-000000000000</id>
                    <parentGroupId>3937ac05-5578-3ca8-0000-000000000000</parentGroupId>
                    <versionedComponentId>faab8056-66ab-3d18-b213-324f367328f2</versionedComponentId>
                    <bulletinLevel>WARN</bulletinLevel>
                    <bundle>
                        <artifact>nifi-ssl-context-service-nar</artifact>
                        <group>org.apache.nifi</group>
                        <version>1.20.0</version>
                    </bundle>
                    <comments></comments>
                    <descriptors>
                        <entry>
                            <key>Keystore Filename</key>
                            <value>
<name>Keystore Filename</name>
                            </value>
                        </entry>
                        <entry>
                            <key>Keystore Password</key>
                            <value>
<name>Keystore Password</name>
                            </value>
                        </entry>
                        <entry>
                            <key>key-password</key>
                            <value>
<name>key-password</name>
                            </value>
                        </entry>
                        <entry>
                            <key>Keystore Type</key>
                            <value>
<name>Keystore Type</name>
                            </value>
                        </entry>
                        <entry>
                            <key>Truststore Filename</key>
                            <value>
<name>Truststore Filename</name>
                            </value>
                        </entry>
                        <entry>
                            <key>Truststore Password</key>
                            <value>
<name>Truststore Password</name>
                            </value>
                        </entry>
                        <entry>
                            <key>Truststore Type</key>
                            <value>
<name>Truststore Type</name>
                            </value>
                        </entry>
                        <entry>
                            <key>SSL Protocol</key>
                            <value>
<name>SSL Protocol</name>
                            </value>
                        </entry>
                    </descriptors>
                    <name>StandardSSLContextService</name>
                    <persistsState>false</persistsState>
                    <properties>
                        <entry>
                            <key>Keystore Filename</key>
                        </entry>
                        <entry>
                            <key>Keystore Password</key>
                        </entry>
                        <entry>
                            <key>key-password</key>
                        </entry>
                        <entry>
                            <key>Keystore Type</key>
                        </entry>
                        <entry>
                            <key>Truststore Filename</key>
                            <value>/Library/Java/JavaVirtualMachines/jdk-1.8.jdk/Contents/Home/jre/lib/security/cacerts</value>
                        </entry>
                        <entry>
                            <key>Truststore Password</key>
                        </entry>
                        <entry>
                            <key>Truststore Type</key>
                            <value>JKS</value>
                        </entry>
                        <entry>
                            <key>SSL Protocol</key>
                            <value>TLS</value>
                        </entry>
                    </properties>
                    <state>ENABLED</state>
                    <type>org.apache.nifi.ssl.StandardSSLContextService</type>
                </controllerServices>
                <processors>
                    <id>11d2269b-4363-39af-0000-000000000000</id>
                    <parentGroupId>3937ac05-5578-3ca8-0000-000000000000</parentGroupId>
                    <position>
                        <x>248.0</x>
                        <y>24.0</y>
                    </position>
                    <versionedComponentId>11d2269b-4363-39af-9cd2-a6be9124ba1e</versionedComponentId>
                    <bundle>
                        <artifact>nifi-standard-nar</artifact>
                        <group>org.apache.nifi</group>
                        <version>1.20.0</version>
                    </bundle>
                    <config>
                        <backoffMechanism>PENALIZE_FLOWFILE</backoffMechanism>
                        <bulletinLevel>WARN</bulletinLevel>
                        <comments></comments>
                        <concurrentlySchedulableTaskCount>1</concurrentlySchedulableTaskCount>
                        <descriptors>
                            <entry>
<key>HTTP Method</key>
<value>
    <name>HTTP Method</name>
</value>
                            </entry>
                            <entry>
<key>Remote URL</key>
<value>
    <name>Remote URL</name>
</value>
                            </entry>
                            <entry>
<key>disable-http2</key>
<value>
    <name>disable-http2</name>
</value>
                            </entry>
                            <entry>
<key>SSL Context Service</key>
<value>
    <identifiesControllerService>org.apache.nifi.ssl.SSLContextService</identifiesControllerService>
    <name>SSL Context Service</name>
</value>
                            </entry>
                            <entry>
<key>Connection Timeout</key>
<value>
    <name>Connection Timeout</name>
</value>
                            </entry>
                            <entry>
<key>Read Timeout</key>
<value>
    <name>Read Timeout</name>
</value>
                            </entry>
                            <entry>
<key>idle-timeout</key>
<value>
    <name>idle-timeout</name>
</value>
                            </entry>
                            <entry>
<key>max-idle-connections</key>
<value>
    <name>max-idle-connections</name>
</value>
                            </entry>
                            <entry>
<key>proxy-configuration-service</key>
<value>
    <identifiesControllerService>org.apache.nifi.proxy.ProxyConfigurationService</identifiesControllerService>
    <name>proxy-configuration-service</name>
</value>
                            </entry>
                            <entry>
<key>Proxy Host</key>
<value>
    <name>Proxy Host</name>
</value>
                            </entry>
                            <entry>
<key>Proxy Port</key>
<value>
    <dependencies>
        <propertyName>Proxy Host</propertyName>
    </dependencies>
    <name>Proxy Port</name>
</value>
                            </entry>
                            <entry>
<key>Proxy Type</key>
<value>
    <dependencies>
        <propertyName>Proxy Host</propertyName>
    </dependencies>
    <name>Proxy Type</name>
</value>
                            </entry>
                            <entry>
<key>invokehttp-proxy-user</key>
<value>
    <dependencies>
        <propertyName>Proxy Host</propertyName>
    </dependencies>
    <name>invokehttp-proxy-user</name>
</value>
                            </entry>
                            <entry>
<key>invokehttp-proxy-password</key>
<value>
    <dependencies>
        <propertyName>Proxy Host</propertyName>
    </dependencies>
    <name>invokehttp-proxy-password</name>
</value>
                            </entry>
                            <entry>
<key>oauth2-access-token-provider</key>
<value>
    <identifiesControllerService>org.apache.nifi.oauth2.OAuth2AccessTokenProvider</identifiesControllerService>
    <name>oauth2-access-token-provider</name>
</value>
                            </entry>
                            <entry>
<key>Basic Authentication Username</key>
<value>
    <name>Basic Authentication Username</name>
</value>
                            </entry>
                            <entry>
<key>Basic Authentication Password</key>
<value>
    <name>Basic Authentication Password</name>
</value>
                            </entry>
                            <entry>
<key>Digest Authentication</key>
<value>
    <dependencies>
        <propertyName>Basic Authentication Username</propertyName>
    </dependencies>
    <name>Digest Authentication</name>
</value>
                            </entry>
                            <entry>
<key>Penalize on "No Retry"</key>
<value>
    <name>Penalize on "No Retry"</name>
</value>
                            </entry>
                            <entry>
<key>send-message-body</key>
<value>
    <dependencies>
        <dependentValues>POST</dependentValues>
        <dependentValues>PATCH</dependentValues>
        <dependentValues>PUT</dependentValues>
        <propertyName>HTTP Method</propertyName>
    </dependencies>
    <name>send-message-body</name>
</value>
                            </entry>
                            <entry>
<key>form-body-form-name</key>
<value>
    <dependencies>
        <dependentValues>true</dependentValues>
        <propertyName>send-message-body</propertyName>
    </dependencies>
    <name>form-body-form-name</name>
</value>
                            </entry>
                            <entry>
<key>set-form-filename</key>
<value>
    <dependencies>
        <propertyName>form-body-form-name</propertyName>
    </dependencies>
    <name>set-form-filename</name>
</value>
                            </entry>
                            <entry>
<key>Use Chunked Encoding</key>
<value>
    <dependencies>
        <dependentValues>POST</dependentValues>
        <dependentValues>PATCH</dependentValues>
        <dependentValues>PUT</dependentValues>
        <propertyName>HTTP Method</propertyName>
    </dependencies>
    <name>Use Chunked Encoding</name>
</value>
                            </entry>
                            <entry>
<key>Content-Encoding</key>
<value>
    <dependencies>
        <dependentValues>POST</dependentValues>
        <dependentValues>PATCH</dependentValues>
        <dependentValues>PUT</dependentValues>
        <propertyName>HTTP Method</propertyName>
    </dependencies>
    <name>Content-Encoding</name>
</value>
                            </entry>
                            <entry>
<key>Content-Type</key>
<value>
    <dependencies>
        <dependentValues>POST</dependentValues>
        <dependentValues>PATCH</dependentValues>
        <dependentValues>PUT</dependentValues>
        <propertyName>HTTP Method</propertyName>
    </dependencies>
    <name>Content-Type</name>
</value>
                            </entry>
                            <entry>
<key>Include Date Header</key>
<value>
    <name>Include Date Header</name>
</value>
                            </entry>
                            <entry>
<key>Attributes to Send</key>
<value>
    <name>Attributes to Send</name>
</value>
                            </entry>
                            <entry>
<key>Useragent</key>
<value>
    <name>Useragent</name>
</value>
                            </entry>
                            <entry>
<key>Put Response Body In Attribute</key>
<value>
    <name>Put Response Body In Attribute</name>
</value>
                            </entry>
                            <entry>
<key>Max Length To Put In Attribute</key>
<value>
    <dependencies>
        <propertyName>Put Response Body In Attribute</propertyName>
    </dependencies>
    <name>Max Length To Put In Attribute</name>
</value>
                            </entry>
                            <entry>
<key>ignore-response-content</key>
<value>
    <name>ignore-response-content</name>
</value>
                            </entry>
                            <entry>
<key>use-etag</key>
<value>
    <name>use-etag</name>
</value>
                            </entry>
                            <entry>
<key>etag-max-cache-size</key>
<value>
    <dependencies>
        <dependentValues>true</dependentValues>
        <propertyName>use-etag</propertyName>
    </dependencies>
    <name>etag-max-cache-size</name>
</value>
                            </entry>
                            <entry>
<key>cookie-strategy</key>
<value>
    <name>cookie-strategy</name>
</value>
                            </entry>
                            <entry>
<key>Always Output Response</key>
<value>
    <name>Always Output Response</name>
</value>
                            </entry>
                            <entry>
<key>flow-file-naming-strategy</key>
<value>
    <name>flow-file-naming-strategy</name>
</value>
                            </entry>
                            <entry>
<key>Add Response Headers to Request</key>
<value>
    <name>Add Response Headers to Request</name>
</value>
                            </entry>
                            <entry>
<key>Follow Redirects</key>
<value>
    <name>Follow Redirects</name>
</value>
                            </entry>
                        </descriptors>
                        <executionNode>ALL</executionNode>
                        <lossTolerant>false</lossTolerant>
                        <maxBackoffPeriod>10 mins</maxBackoffPeriod>
                        <penaltyDuration>30 sec</penaltyDuration>
                        <properties>
                            <entry>
<key>HTTP Method</key>
<value>GET</value>
                            </entry>
                            <entry>
<key>Remote URL</key>
<value>https://raw.githubusercontent.com/Avani10/Facebook-Data-Analysis/master/pseudo_facebook.csv</value>
                            </entry>
                            <entry>
<key>disable-http2</key>
<value>False</value>
                            </entry>
                            <entry>
<key>SSL Context Service</key>
<value>faab8056-66ab-3d18-0000-000000000000</value>
                            </entry>
                            <entry>
<key>Connection Timeout</key>
<value>5 secs</value>
                            </entry>
                            <entry>
<key>Read Timeout</key>
<value>15 secs</value>
                            </entry>
                            <entry>
<key>idle-timeout</key>
<value>5 mins</value>
                            </entry>
                            <entry>
<key>max-idle-connections</key>
<value>5</value>
                            </entry>
                            <entry>
<key>proxy-configuration-service</key>
                            </entry>
                            <entry>
<key>Proxy Host</key>
                            </entry>
                            <entry>
<key>Proxy Port</key>
                            </entry>
                            <entry>
<key>Proxy Type</key>
<value>http</value>
                            </entry>
                            <entry>
<key>invokehttp-proxy-user</key>
                            </entry>
                            <entry>
<key>invokehttp-proxy-password</key>
                            </entry>
                            <entry>
<key>oauth2-access-token-provider</key>
                            </entry>
                            <entry>
<key>Basic Authentication Username</key>
                            </entry>
                            <entry>
<key>Basic Authentication Password</key>
                            </entry>
                            <entry>
<key>Digest Authentication</key>
<value>false</value>
                            </entry>
                            <entry>
<key>Penalize on "No Retry"</key>
<value>false</value>
                            </entry>
                            <entry>
<key>send-message-body</key>
<value>true</value>
                            </entry>
                            <entry>
<key>form-body-form-name</key>
                            </entry>
                            <entry>
<key>set-form-filename</key>
<value>true</value>
                            </entry>
                            <entry>
<key>Use Chunked Encoding</key>
<value>false</value>
                            </entry>
                            <entry>
<key>Content-Encoding</key>
<value>DISABLED</value>
                            </entry>
                            <entry>
<key>Content-Type</key>
<value>${mime.type}</value>
                            </entry>
                            <entry>
<key>Include Date Header</key>
<value>True</value>
                            </entry>
                            <entry>
<key>Attributes to Send</key>
                            </entry>
                            <entry>
<key>Useragent</key>
                            </entry>
                            <entry>
<key>Put Response Body In Attribute</key>
                            </entry>
                            <entry>
<key>Max Length To Put In Attribute</key>
<value>256</value>
                            </entry>
                            <entry>
<key>ignore-response-content</key>
<value>false</value>
                            </entry>
                            <entry>
<key>use-etag</key>
<value>false</value>
                            </entry>
                            <entry>
<key>etag-max-cache-size</key>
<value>10MB</value>
                            </entry>
                            <entry>
<key>cookie-strategy</key>
<value>DISABLED</value>
                            </entry>
                            <entry>
<key>Always Output Response</key>
<value>false</value>
                            </entry>
                            <entry>
<key>flow-file-naming-strategy</key>
<value>URL_PATH</value>
                            </entry>
                            <entry>
<key>Add Response Headers to Request</key>
<value>false</value>
                            </entry>
                            <entry>
<key>Follow Redirects</key>
<value>True</value>
                            </entry>
                        </properties>
                        <retryCount>10</retryCount>
                        <runDurationMillis>0</runDurationMillis>
                        <schedulingPeriod>60 sec</schedulingPeriod>
                        <schedulingStrategy>TIMER_DRIVEN</schedulingStrategy>
                        <yieldDuration>1 sec</yieldDuration>
                    </config>
                    <executionNodeRestricted>false</executionNodeRestricted>
                    <name>InvokeHTTP</name>
                    <relationships>
                        <autoTerminate>true</autoTerminate>
                        <name>Failure</name>
                        <retry>false</retry>
                    </relationships>
                    <relationships>
                        <autoTerminate>true</autoTerminate>
                        <name>No Retry</name>
                        <retry>false</retry>
                    </relationships>
                    <relationships>
                        <autoTerminate>true</autoTerminate>
                        <name>Original</name>
                        <retry>false</retry>
                    </relationships>
                    <relationships>
                        <autoTerminate>false</autoTerminate>
                        <name>Response</name>
                        <retry>false</retry>
                    </relationships>
                    <relationships>
                        <autoTerminate>true</autoTerminate>
                        <name>Retry</name>
                        <retry>false</retry>
                    </relationships>
                    <state>STOPPED</state>
                    <style/>
                    <type>org.apache.nifi.processors.standard.InvokeHTTP</type>
                </processors>
                <processors>
                    <id>79315e66-d893-3ed7-0000-000000000000</id>
                    <parentGroupId>3937ac05-5578-3ca8-0000-000000000000</parentGroupId>
                    <position>
                        <x>720.0</x>
                        <y>24.0</y>
                    </position>
                    <versionedComponentId>79315e66-d893-3ed7-9816-149dd96bc8d5</versionedComponentId>
                    <bundle>
                        <artifact>nifi-standard-nar</artifact>
                        <group>org.apache.nifi</group>
                        <version>1.20.0</version>
                    </bundle>
                    <config>
                        <backoffMechanism>PENALIZE_FLOWFILE</backoffMechanism>
                        <bulletinLevel>WARN</bulletinLevel>
                        <comments></comments>
                        <concurrentlySchedulableTaskCount>1</concurrentlySchedulableTaskCount>
                        <descriptors>
                            <entry>
<key>URL</key>
<value>
    <name>URL</name>
</value>
                            </entry>
                            <entry>
<key>Filename</key>
<value>
    <name>Filename</name>
</value>
                            </entry>
                            <entry>
<key>SSL Context Service</key>
<value>
    <identifiesControllerService>org.apache.nifi.ssl.SSLContextService</identifiesControllerService>
    <name>SSL Context Service</name>
</value>
                            </entry>
                            <entry>
<key>Username</key>
<value>
    <name>Username</name>
</value>
                            </entry>
                            <entry>
<key>Password</key>
<value>
    <name>Password</name>
</value>
                            </entry>
                            <entry>
<key>Connection Timeout</key>
<value>
    <name>Connection Timeout</name>
</value>
                            </entry>
                            <entry>
<key>Data Timeout</key>
<value>
    <name>Data Timeout</name>
</value>
                            </entry>
                            <entry>
<key>User Agent</key>
<value>
    <name>User Agent</name>
</value>
                            </entry>
                            <entry>
<key>Accept Content-Type</key>
<value>
    <name>Accept Content-Type</name>
</value>
                            </entry>
                            <entry>
<key>Follow Redirects</key>
<value>
    <name>Follow Redirects</name>
</value>
                            </entry>
                            <entry>
<key>redirect-cookie-policy</key>
<value>
    <name>redirect-cookie-policy</name>
</value>
                            </entry>
                            <entry>
<key>proxy-configuration-service</key>
<value>
    <identifiesControllerService>org.apache.nifi.proxy.ProxyConfigurationService</identifiesControllerService>
    <name>proxy-configuration-service</name>
</value>
                            </entry>
                            <entry>
<key>Proxy Host</key>
<value>
    <name>Proxy Host</name>
</value>
                            </entry>
                            <entry>
<key>Proxy Port</key>
<value>
    <name>Proxy Port</name>
</value>
                            </entry>
                        </descriptors>
                        <executionNode>ALL</executionNode>
                        <lossTolerant>false</lossTolerant>
                        <maxBackoffPeriod>10 mins</maxBackoffPeriod>
                        <penaltyDuration>30 sec</penaltyDuration>
                        <properties>
                            <entry>
<key>URL</key>
<value>https://raw.githubusercontent.com/Avani10/Facebook-Data-Analysis/master/pseudo_facebook.csv</value>
                            </entry>
                            <entry>
<key>Filename</key>
<value>pseudo_facebook.csv</value>
                            </entry>
                            <entry>
<key>SSL Context Service</key>
<value>faab8056-66ab-3d18-0000-000000000000</value>
                            </entry>
                            <entry>
<key>Username</key>
                            </entry>
                            <entry>
<key>Password</key>
                            </entry>
                            <entry>
<key>Connection Timeout</key>
<value>30 sec</value>
                            </entry>
                            <entry>
<key>Data Timeout</key>
<value>30 sec</value>
                            </entry>
                            <entry>
<key>User Agent</key>
                            </entry>
                            <entry>
<key>Accept Content-Type</key>
                            </entry>
                            <entry>
<key>Follow Redirects</key>
<value>false</value>
                            </entry>
                            <entry>
<key>redirect-cookie-policy</key>
<value>default</value>
                            </entry>
                            <entry>
<key>proxy-configuration-service</key>
                            </entry>
                            <entry>
<key>Proxy Host</key>
                            </entry>
                            <entry>
<key>Proxy Port</key>
                            </entry>
                        </properties>
                        <retryCount>10</retryCount>
                        <runDurationMillis>0</runDurationMillis>
                        <schedulingPeriod>0 sec</schedulingPeriod>
                        <schedulingStrategy>TIMER_DRIVEN</schedulingStrategy>
                        <yieldDuration>1 sec</yieldDuration>
                    </config>
                    <executionNodeRestricted>false</executionNodeRestricted>
                    <name>GetHTTP</name>
                    <relationships>
                        <autoTerminate>false</autoTerminate>
                        <name>success</name>
                        <retry>false</retry>
                    </relationships>
                    <state>STOPPED</state>
                    <style/>
                    <type>org.apache.nifi.processors.standard.GetHTTP</type>
                </processors>
                <processors>
                    <id>977518bf-ca05-320d-0000-000000000000</id>
                    <parentGroupId>3937ac05-5578-3ca8-0000-000000000000</parentGroupId>
                    <position>
                        <x>328.0</x>
                        <y>336.0</y>
                    </position>
                    <versionedComponentId>977518bf-ca05-320d-aebf-e1dab3178566</versionedComponentId>
                    <bundle>
                        <artifact>nifi-hadoop-nar</artifact>
                        <group>org.apache.nifi</group>
                        <version>1.20.0</version>
                    </bundle>
                    <config>
                        <backoffMechanism>PENALIZE_FLOWFILE</backoffMechanism>
                        <bulletinLevel>WARN</bulletinLevel>
                        <comments></comments>
                        <concurrentlySchedulableTaskCount>1</concurrentlySchedulableTaskCount>
                        <descriptors>
                            <entry>
<key>Hadoop Configuration Resources</key>
<value>
    <name>Hadoop Configuration Resources</name>
</value>
                            </entry>
                            <entry>
<key>kerberos-credentials-service</key>
<value>
    <identifiesControllerService>org.apache.nifi.kerberos.KerberosCredentialsService</identifiesControllerService>
    <name>kerberos-credentials-service</name>
</value>
                            </entry>
                            <entry>
<key>kerberos-user-service</key>
<value>
    <identifiesControllerService>org.apache.nifi.kerberos.KerberosUserService</identifiesControllerService>
    <name>kerberos-user-service</name>
</value>
                            </entry>
                            <entry>
<key>Kerberos Principal</key>
<value>
    <name>Kerberos Principal</name>
</value>
                            </entry>
                            <entry>
<key>Kerberos Keytab</key>
<value>
    <name>Kerberos Keytab</name>
</value>
                            </entry>
                            <entry>
<key>Kerberos Password</key>
<value>
    <name>Kerberos Password</name>
</value>
                            </entry>
                            <entry>
<key>Kerberos Relogin Period</key>
<value>
    <name>Kerberos Relogin Period</name>
</value>
                            </entry>
                            <entry>
<key>Additional Classpath Resources</key>
<value>
    <name>Additional Classpath Resources</name>
</value>
                            </entry>
                            <entry>
<key>Directory</key>
<value>
    <name>Directory</name>
</value>
                            </entry>
                            <entry>
<key>Conflict Resolution Strategy</key>
<value>
    <name>Conflict Resolution Strategy</name>
</value>
                            </entry>
                            <entry>
<key>writing-strategy</key>
<value>
    <name>writing-strategy</name>
</value>
                            </entry>
                            <entry>
<key>Block Size</key>
<value>
    <name>Block Size</name>
</value>
                            </entry>
                            <entry>
<key>IO Buffer Size</key>
<value>
    <name>IO Buffer Size</name>
</value>
                            </entry>
                            <entry>
<key>Replication</key>
<value>
    <name>Replication</name>
</value>
                            </entry>
                            <entry>
<key>Permissions umask</key>
<value>
    <name>Permissions umask</name>
</value>
                            </entry>
                            <entry>
<key>Remote Owner</key>
<value>
    <name>Remote Owner</name>
</value>
                            </entry>
                            <entry>
<key>Remote Group</key>
<value>
    <name>Remote Group</name>
</value>
                            </entry>
                            <entry>
<key>Compression codec</key>
<value>
    <name>Compression codec</name>
</value>
                            </entry>
                            <entry>
<key>Ignore Locality</key>
<value>
    <name>Ignore Locality</name>
</value>
                            </entry>
                        </descriptors>
                        <executionNode>ALL</executionNode>
                        <lossTolerant>false</lossTolerant>
                        <maxBackoffPeriod>10 mins</maxBackoffPeriod>
                        <penaltyDuration>30 sec</penaltyDuration>
                        <properties>
                            <entry>
<key>Hadoop Configuration Resources</key>
<value>/Users/AKB_CIM/hadoop-3.3.5/etc/hadoop/hdfs-site.xml, /Users/AKB_CIM/hadoop-3.3.5/etc/hadoop/core-site.xml</value>
                            </entry>
                            <entry>
<key>kerberos-credentials-service</key>
                            </entry>
                            <entry>
<key>kerberos-user-service</key>
                            </entry>
                            <entry>
<key>Kerberos Principal</key>
                            </entry>
                            <entry>
<key>Kerberos Keytab</key>
                            </entry>
                            <entry>
<key>Kerberos Password</key>
                            </entry>
                            <entry>
<key>Kerberos Relogin Period</key>
<value>4 hours</value>
                            </entry>
                            <entry>
<key>Additional Classpath Resources</key>
                            </entry>
                            <entry>
<key>Directory</key>
<value>/user/hive/project</value>
                            </entry>
                            <entry>
<key>Conflict Resolution Strategy</key>
<value>replace</value>
                            </entry>
                            <entry>
<key>writing-strategy</key>
<value>writeAndRename</value>
                            </entry>
                            <entry>
<key>Block Size</key>
                            </entry>
                            <entry>
<key>IO Buffer Size</key>
                            </entry>
                            <entry>
<key>Replication</key>
                            </entry>
                            <entry>
<key>Permissions umask</key>
                            </entry>
                            <entry>
<key>Remote Owner</key>
                            </entry>
                            <entry>
<key>Remote Group</key>
                            </entry>
                            <entry>
<key>Compression codec</key>
<value>NONE</value>
                            </entry>
                            <entry>
<key>Ignore Locality</key>
<value>false</value>
                            </entry>
                        </properties>
                        <retryCount>10</retryCount>
                        <runDurationMillis>0</runDurationMillis>
                        <schedulingPeriod>60 sec</schedulingPeriod>
                        <schedulingStrategy>TIMER_DRIVEN</schedulingStrategy>
                        <yieldDuration>1 sec</yieldDuration>
                    </config>
                    <executionNodeRestricted>false</executionNodeRestricted>
                    <name>PutHDFS</name>
                    <relationships>
                        <autoTerminate>true</autoTerminate>
                        <name>failure</name>
                        <retry>false</retry>
                    </relationships>
                    <relationships>
                        <autoTerminate>true</autoTerminate>
                        <name>success</name>
                        <retry>false</retry>
                    </relationships>
                    <state>STOPPED</state>
                    <style/>
                    <type>org.apache.nifi.processors.hadoop.PutHDFS</type>
                </processors>
                <processors>
                    <id>f305bd82-323d-3bcb-0000-000000000000</id>
                    <parentGroupId>3937ac05-5578-3ca8-0000-000000000000</parentGroupId>
                    <position>
                        <x>824.0</x>
                        <y>320.0</y>
                    </position>
                    <versionedComponentId>f305bd82-323d-3bcb-850e-0cc26b69df3d</versionedComponentId>
                    <bundle>
                        <artifact>nifi-standard-nar</artifact>
                        <group>org.apache.nifi</group>
                        <version>1.20.0</version>
                    </bundle>
                    <config>
                        <backoffMechanism>PENALIZE_FLOWFILE</backoffMechanism>
                        <bulletinLevel>WARN</bulletinLevel>
                        <comments></comments>
                        <concurrentlySchedulableTaskCount>1</concurrentlySchedulableTaskCount>
                        <descriptors>
                            <entry>
<key>Directory</key>
<value>
    <name>Directory</name>
</value>
                            </entry>
                            <entry>
<key>Conflict Resolution Strategy</key>
<value>
    <name>Conflict Resolution Strategy</name>
</value>
                            </entry>
                            <entry>
<key>Create Missing Directories</key>
<value>
    <name>Create Missing Directories</name>
</value>
                            </entry>
                            <entry>
<key>Maximum File Count</key>
<value>
    <name>Maximum File Count</name>
</value>
                            </entry>
                            <entry>
<key>Last Modified Time</key>
<value>
    <name>Last Modified Time</name>
</value>
                            </entry>
                            <entry>
<key>Permissions</key>
<value>
    <name>Permissions</name>
</value>
                            </entry>
                            <entry>
<key>Owner</key>
<value>
    <name>Owner</name>
</value>
                            </entry>
                            <entry>
<key>Group</key>
<value>
    <name>Group</name>
</value>
                            </entry>
                        </descriptors>
                        <executionNode>ALL</executionNode>
                        <lossTolerant>false</lossTolerant>
                        <maxBackoffPeriod>10 mins</maxBackoffPeriod>
                        <penaltyDuration>30 sec</penaltyDuration>
                        <properties>
                            <entry>
<key>Directory</key>
<value>/Users/AKB_CIM/nifi_tutorials/input_files/tmp/books_target_dir</value>
                            </entry>
                            <entry>
<key>Conflict Resolution Strategy</key>
<value>replace</value>
                            </entry>
                            <entry>
<key>Create Missing Directories</key>
<value>true</value>
                            </entry>
                            <entry>
<key>Maximum File Count</key>
                            </entry>
                            <entry>
<key>Last Modified Time</key>
                            </entry>
                            <entry>
<key>Permissions</key>
                            </entry>
                            <entry>
<key>Owner</key>
                            </entry>
                            <entry>
<key>Group</key>
                            </entry>
                        </properties>
                        <retryCount>10</retryCount>
                        <runDurationMillis>0</runDurationMillis>
                        <schedulingPeriod>0 sec</schedulingPeriod>
                        <schedulingStrategy>TIMER_DRIVEN</schedulingStrategy>
                        <yieldDuration>1 sec</yieldDuration>
                    </config>
                    <executionNodeRestricted>false</executionNodeRestricted>
                    <name>PutFile</name>
                    <relationships>
                        <autoTerminate>true</autoTerminate>
                        <name>failure</name>
                        <retry>false</retry>
                    </relationships>
                    <relationships>
                        <autoTerminate>true</autoTerminate>
                        <name>success</name>
                        <retry>false</retry>
                    </relationships>
                    <state>STOPPED</state>
                    <style/>
                    <type>org.apache.nifi.processors.standard.PutFile</type>
                </processors>
            </contents>
            <defaultBackPressureDataSizeThreshold>1 GB</defaultBackPressureDataSizeThreshold>
            <defaultBackPressureObjectThreshold>10000</defaultBackPressureObjectThreshold>
            <defaultFlowFileExpiration>0 sec</defaultFlowFileExpiration>
            <flowfileConcurrency>UNBOUNDED</flowfileConcurrency>
            <flowfileOutboundPolicy>STREAM_WHEN_AVAILABLE</flowfileOutboundPolicy>
            <name>get data from url into HDFS</name>
            <variables/>
        </processGroups>
    </snippet>
    <timestamp>07/17/2023 14:28:50 BST</timestamp>
</template>
